[{"line":1,"elements":[{"start_timestamp":"2025-03-24T13:54:33.404Z","line":17,"name":"Verify contacts details for mule-salesforce-sys-api in sys environment for ticket CSR-3543","description":"","id":"verify-contacts-details-for-mule-salesforce-sys-api-in-sys-environment-for-ticket-csr-3543","type":"scenario","keyword":"Scenario Outline","steps":[{"name":"karate.configure('ssl',true)","result":{"duration":1528000,"status":"passed"},"match":{"location":"karate","arguments":[]},"keyword":"*","line":5,"doc_string":{"content_type":"","value":"09:54:33.404 karate.env system property was: null \n","line":5}},{"name":"url 'https:\/\/mule-wft.qa.medpro.com\/api\/salesforce\/sys\/v1\/contacts?lastName=Hanson&orderBy=name&order=desc'","result":{"duration":763800,"status":"passed"},"match":{"location":"karate","arguments":[]},"keyword":"Given","line":6},{"name":"method get","result":{"duration":403263800,"status":"passed"},"match":{"location":"karate","arguments":[]},"keyword":"When","line":7},{"name":"status 200","result":{"duration":13000,"status":"passed"},"match":{"location":"karate","arguments":[]},"keyword":"Then","line":8},{"name":"def length1 = karate.jsonPath(response, \"$.content.[*].id\")","result":{"duration":727900,"status":"passed"},"match":{"location":"karate","arguments":[]},"keyword":"*","line":10},{"name":"print length1","result":{"duration":637500,"status":"passed"},"match":{"location":"karate","arguments":[]},"keyword":"And","line":11,"doc_string":{"content_type":"","value":"09:54:33.813 [print] [\n  \"0037j00000csI9CAAU\"\n]\n \n","line":11}},{"name":"def count = length1.length","result":{"duration":330100,"status":"passed"},"match":{"location":"karate","arguments":[]},"keyword":"*","line":12},{"name":"match count == 1","result":{"duration":482700,"status":"passed"},"match":{"location":"karate","arguments":[]},"keyword":"*","line":13}],"tags":[]}],"name":"wfSImuleSoft\/sysApi\/getContactsDetailsCSR3543Sys.feature","description":"Getting mule-salesforce-sys-api to test contacts details for ticket CSR-3543","id":"getting-mule-salesforce-sys-api-to-test-contacts-details-for-ticket-csr-3543","keyword":"Feature","uri":"wfSImuleSoft\/sysApi\/getContactsDetailsCSR3543Sys.feature"}]