[{"line":1,"elements":[{"start_timestamp":"2025-02-25T16:39:29.483Z","line":20,"name":"To verify the File Process in Proc environment for ticket CSR-3537","description":"","id":"to-verify-the-file-process-in-proc-environment-for-ticket-csr-3537","type":"scenario","keyword":"Scenario Outline","steps":[{"name":"karate.configure('ssl',true)","result":{"duration":1729300,"status":"passed"},"match":{"location":"karate","arguments":[]},"keyword":"*","line":7,"doc_string":{"content_type":"","value":"11:39:29.484 karate.env system property was: null \n","line":7}},{"name":"url 'https:\/\/mule-wft.qa.medpro.com\/api\/fileprocesses\/prc\/v1\/fileprocess?page=1&pagesize=10&sortexpression=Id&sortorder=desc'","result":{"duration":549300,"status":"passed"},"match":{"location":"karate","arguments":[]},"keyword":"Given","line":8},{"name":"method get","result":{"duration":46738500,"status":"passed"},"match":{"location":"karate","arguments":[]},"keyword":"When","line":9},{"name":"status 200","result":{"duration":14600,"status":"passed"},"match":{"location":"karate","arguments":[]},"keyword":"Then","line":10},{"name":"def length1 = karate.jsonPath(response, \"$.content.[*].id\")","result":{"duration":1111500,"status":"passed"},"match":{"location":"karate","arguments":[]},"keyword":"*","line":13},{"name":"print length1","result":{"duration":478700,"status":"passed"},"match":{"location":"karate","arguments":[]},"keyword":"And","line":14,"doc_string":{"content_type":"","value":"11:39:29.537 [print] [\n  173175,\n  173174,\n  173173,\n  173172,\n  173171,\n  173170,\n  173169,\n  173168,\n  173167,\n  173166\n]\n \n","line":14}},{"name":"def count = length1.length","result":{"duration":223300,"status":"passed"},"match":{"location":"karate","arguments":[]},"keyword":"*","line":15},{"name":"match count == 10","result":{"duration":1562600,"status":"passed"},"match":{"location":"karate","arguments":[]},"keyword":"*","line":16}],"tags":[]}],"name":"wfSImuleSoft\/procApi\/getFileProcessProcCSR3537.feature","description":"Getting mule-fileprocesses-proc-api GetFileProcess for ticket CSR-3537","id":"getting-mule-fileprocesses-proc-api-getfileprocess-for-ticket-csr-3537","keyword":"Feature","uri":"wfSImuleSoft\/procApi\/getFileProcessProcCSR3537.feature"}]